odoo9_addon_mgmtsystem_manual-9.0.1.0.0.99.dev16-py2.7-nspkg.pth
odoo9_addon_mgmtsystem_manual-9.0.1.0.0.99.dev16.dist-info/DESCRIPTION.rst
odoo9_addon_mgmtsystem_manual-9.0.1.0.0.99.dev16.dist-info/METADATA
odoo9_addon_mgmtsystem_manual-9.0.1.0.0.99.dev16.dist-info/RECORD
odoo9_addon_mgmtsystem_manual-9.0.1.0.0.99.dev16.dist-info/WHEEL
odoo9_addon_mgmtsystem_manual-9.0.1.0.0.99.dev16.dist-info/metadata.json
odoo9_addon_mgmtsystem_manual-9.0.1.0.0.99.dev16.dist-info/namespace_packages.txt
odoo9_addon_mgmtsystem_manual-9.0.1.0.0.99.dev16.dist-info/top_level.txt
odoo_addons/mgmtsystem_manual/README.rst
odoo_addons/mgmtsystem_manual/__init__.py
odoo_addons/mgmtsystem_manual/__openerp__.py
odoo_addons/mgmtsystem_manual/data/mgmtsystem_manual.xml
odoo_addons/mgmtsystem_manual/i18n/ar.po
odoo_addons/mgmtsystem_manual/i18n/bg.po
odoo_addons/mgmtsystem_manual/i18n/bs.po
odoo_addons/mgmtsystem_manual/i18n/cs.po
odoo_addons/mgmtsystem_manual/i18n/da.po
odoo_addons/mgmtsystem_manual/i18n/de.po
odoo_addons/mgmtsystem_manual/i18n/en_GB.po
odoo_addons/mgmtsystem_manual/i18n/es.po
odoo_addons/mgmtsystem_manual/i18n/es_AR.po
odoo_addons/mgmtsystem_manual/i18n/es_CO.po
odoo_addons/mgmtsystem_manual/i18n/es_CR.po
odoo_addons/mgmtsystem_manual/i18n/es_DO.po
odoo_addons/mgmtsystem_manual/i18n/es_EC.po
odoo_addons/mgmtsystem_manual/i18n/es_MX.po
odoo_addons/mgmtsystem_manual/i18n/es_PY.po
odoo_addons/mgmtsystem_manual/i18n/es_VE.po
odoo_addons/mgmtsystem_manual/i18n/et.po
odoo_addons/mgmtsystem_manual/i18n/eu.po
odoo_addons/mgmtsystem_manual/i18n/fa.po
odoo_addons/mgmtsystem_manual/i18n/fr.po
odoo_addons/mgmtsystem_manual/i18n/he.po
odoo_addons/mgmtsystem_manual/i18n/hr.po
odoo_addons/mgmtsystem_manual/i18n/hu.po
odoo_addons/mgmtsystem_manual/i18n/id.po
odoo_addons/mgmtsystem_manual/i18n/it.po
odoo_addons/mgmtsystem_manual/i18n/ja.po
odoo_addons/mgmtsystem_manual/i18n/ko.po
odoo_addons/mgmtsystem_manual/i18n/lt.po
odoo_addons/mgmtsystem_manual/i18n/lv.po
odoo_addons/mgmtsystem_manual/i18n/mgmtsystem_manual.pot
odoo_addons/mgmtsystem_manual/i18n/mk.po
odoo_addons/mgmtsystem_manual/i18n/mn.po
odoo_addons/mgmtsystem_manual/i18n/nb.po
odoo_addons/mgmtsystem_manual/i18n/nl_BE.po
odoo_addons/mgmtsystem_manual/i18n/nn.po
odoo_addons/mgmtsystem_manual/i18n/pt_BR.po
odoo_addons/mgmtsystem_manual/i18n/sk.po
odoo_addons/mgmtsystem_manual/i18n/sl.po
odoo_addons/mgmtsystem_manual/i18n/sr.po
odoo_addons/mgmtsystem_manual/i18n/sr@latin.po
